code_workspace_sync/__init__.py
code_workspace_sync-0.1.1.dist-info/WHEEL
code_workspace_sync-0.1.1.dist-info/entry_points.txt
code_workspace_sync-0.1.1.dist-info/METADATA
code_workspace_sync-0.1.1.dist-info/RECORD
