Metadata-Version: 2.3
Name: code-workspace-sync
Version: 0.1.1
Summary: synchronize a VS Code workspace with directories in a source repositories folder
Author: W. J. Meijer
Author-email: W. J. Meijer <houterm@gmail.com>
Requires-Python: >=3.12
